nt_summary_stats/__init__.py
nt_summary_stats/_backend.py
nt_summary_stats/_native.cpython-311-x86_64-linux-gnu.so
nt_summary_stats/core.py
nt_summary_stats/event.py
nt_summary_stats-1.0.dist-info/METADATA
nt_summary_stats-1.0.dist-info/WHEEL
nt_summary_stats-1.0.dist-info/top_level.txt
nt_summary_stats-1.0.dist-info/RECORD
