Metadata-Version: 2.1
Name: nt-summary-stats
Version: 1.0
Summary: Fast computation of traditional summary statistics for neutrino telescopes
Author-email: "Felix J. Yu" <felixyu@g.harvard.edu>
Project-URL: Homepage, https://github.com/felixyu7/nt_summary_stats
Project-URL: Repository, https://github.com/felixyu7/nt_summary_stats
Project-URL: Issues, https://github.com/felixyu7/nt_summary_stats/issues
Keywords: neutrino,telescope,summary,statistics,icecube,physics
Classifier: Development Status :: 3 - Alpha
Classifier: Intended Audience :: Science/Research
Classifier: Topic :: Scientific/Engineering :: Physics
Classifier: License :: OSI Approved :: MIT License
Classifier: Programming Language :: Python :: 3
Classifier: Programming Language :: Python :: 3.8
Classifier: Programming Language :: Python :: 3.9
Classifier: Programming Language :: Python :: 3.10
Classifier: Programming Language :: Python :: 3.11
Classifier: Programming Language :: C++
Requires-Python: >=3.8
Requires-Dist: numpy>=1.20.0
Provides-Extra: dev
Requires-Dist: pytest>=6.0; extra == "dev"
Requires-Dist: pytest-cov; extra == "dev"
Requires-Dist: black; extra == "dev"
Requires-Dist: flake8; extra == "dev"
Requires-Dist: pybind11>=2.11; extra == "dev"
